helion/__init__.py
helion/_compat.py
helion/_compile_time.py
helion/_testing.py
helion/_utils.py
helion/exc.py
helion/_compiler/__init__.py
helion/_compiler/ast_extension.py
helion/_compiler/ast_read_writes.py
helion/_compiler/aten_lowering.py
helion/_compiler/compile_environment.py
helion/_compiler/device_function.py
helion/_compiler/device_ir.py
helion/_compiler/dtype_utils.py
helion/_compiler/generate_ast.py
helion/_compiler/helper_function.py
helion/_compiler/host_function.py
helion/_compiler/indexing_strategy.py
helion/_compiler/inductor_lowering.py
helion/_compiler/inductor_lowering_extra.py
helion/_compiler/lift_closures.py
helion/_compiler/loop_dependency_checker.py
helion/_compiler/matmul_utils.py
helion/_compiler/node_masking.py
helion/_compiler/output_header.py
helion/_compiler/output_lines.py
helion/_compiler/program_id.py
helion/_compiler/reduction_strategy.py
helion/_compiler/roll_reduction.py
helion/_compiler/source_location.py
helion/_compiler/static_loop_unroller.py
helion/_compiler/tensor_utils.py
helion/_compiler/tile_dispatch.py
helion/_compiler/tile_strategy.py
helion/_compiler/traceback_compat.py
helion/_compiler/type_printer.py
helion/_compiler/type_propagation.py
helion/_compiler/utils.py
helion/_compiler/variable_origin.py
helion/_logging/__init__.py
helion/_logging/_internal.py
helion/autotuner/__init__.py
helion/autotuner/base_cache.py
helion/autotuner/base_search.py
helion/autotuner/benchmarking.py
helion/autotuner/block_id_sequence.py
helion/autotuner/config_fragment.py
helion/autotuner/config_generation.py
helion/autotuner/config_spec.py
helion/autotuner/de_surrogate_hybrid.py
helion/autotuner/differential_evolution.py
helion/autotuner/effort_profile.py
helion/autotuner/finite_search.py
helion/autotuner/local_cache.py
helion/autotuner/logger.py
helion/autotuner/pattern_search.py
helion/autotuner/progress_bar.py
helion/autotuner/random_search.py
helion/autotuner/surrogate_pattern_search.py
helion/language/__init__.py
helion-0.2.9.dist-info/METADATA
helion-0.2.9.dist-info/WHEEL
helion-0.2.9.dist-info/licenses/LICENSE
helion-0.2.9.dist-info/RECORD
