Metadata-Version: 2.4
Name: helion
Version: 0.2.9
Summary: A Python-embedded DSL that makes it easy to write ML kernels
Project-URL: Homepage, https://github.com/pytorch/helion
Project-URL: Issues, https://github.com/pytorch/helion/issues
Author-email: Jason Ansel <jansel@meta.com>
License: Copyright (c) Meta Platforms, Inc. and affiliates.
License-File: LICENSE
Classifier: Operating System :: OS Independent
Classifier: Programming Language :: Python :: 3
Requires-Python: >=3.10
Requires-Dist: filecheck
Requires-Dist: numpy
Requires-Dist: psutil
Requires-Dist: rich
Requires-Dist: scikit-learn>=1.3.0
Requires-Dist: typing-extensions>=4.0.0
Provides-Extra: dev
Requires-Dist: expecttest; extra == 'dev'
Requires-Dist: hypothesis; extra == 'dev'
Requires-Dist: pre-commit; extra == 'dev'
Requires-Dist: pytest; extra == 'dev'
Requires-Dist: pytest-timeout; extra == 'dev'
Provides-Extra: docs
Requires-Dist: docutils<0.21,==0.18.1; extra == 'docs'
Requires-Dist: linkify-it-py; extra == 'docs'
Requires-Dist: myst-parser; extra == 'docs'
Requires-Dist: pillow; extra == 'docs'
Requires-Dist: pytorch-sphinx-theme2==0.2.0; extra == 'docs'
Requires-Dist: sphinx-autobuild; extra == 'docs'
Requires-Dist: sphinx-autodoc-typehints; extra == 'docs'
Requires-Dist: sphinx-design==0.6.1; extra == 'docs'
Requires-Dist: sphinx-gallery==0.14.0; extra == 'docs'
Requires-Dist: sphinx-sitemap==2.7.1; extra == 'docs'
Requires-Dist: sphinx==7.2.6; extra == 'docs'
Requires-Dist: sphinxcontrib-katex==0.9.10; extra == 'docs'
Requires-Dist: sphinxcontrib-mermaid==1.0.0; extra == 'docs'
Requires-Dist: sphinxext-opengraph; extra == 'docs'
Requires-Dist: torch; extra == 'docs'
